ml_autoencoders/__init__.py
ml_autoencoders/text_reader.py
ml_autoencoders/data/my_code.py
ml_autoencoders-0.1.dist-info/METADATA
ml_autoencoders-0.1.dist-info/WHEEL
ml_autoencoders-0.1.dist-info/top_level.txt
ml_autoencoders-0.1.dist-info/RECORD
